diva/__init__.py
diva/arrows/simple_draw_detected_object_set.py
diva/arrows/__init__.py
diva/utils/utils.so
diva/utils/__init__.py
diva/etc/image_experiment.yml
diva/etc/darknet.config
diva/etc/video_experiment.yml
diva/etc/image_list.txt
diva/scripts/__init__.py
diva/scripts/cli_helpers/cleanup_chunk.py
diva/scripts/cli_helpers/generate_experiments.py
diva/scripts/cli_helpers/merge_videos.py
diva/scripts/cli_helpers/cleanup_experiment.py
diva/.libs/libxcb-65da195c.so.1.1.0
diva/.libs/libzlib-7ac6c2af.so
diva/.libs/libXau-00ec42fe.so.6.0.0
diva/.libs/libxcb-shape-25c2b258.so.0.0.0
diva/.libs/libxcb-xfixes-9be3ba6f.so.0.0.0
diva/.libs/libxcb-shm-7a199f70.so.0.0.0
diva/processes/simple_detector_process.py
diva/processes/register_cpp_processes.py
diva/processes/image_viewer_process.py
diva/processes/__init__.py
diva/lib/libdiva_utils.a
diva/lib/processes/diva_processes.so
diva_framework-0.0.6.data/scripts/cleanup_chunk.py
diva_framework-0.0.6.data/scripts/generate_experiments.py
diva_framework-0.0.6.data/scripts/merge_videos.py
diva_framework-0.0.6.data/scripts/cleanup_experiment.py
diva_framework-0.0.6.dist-info/top_level.txt
diva_framework-0.0.6.dist-info/entry_points.txt
diva_framework-0.0.6.dist-info/WHEEL
diva_framework-0.0.6.dist-info/METADATA
diva_framework-0.0.6.dist-info/RECORD
