Metadata-Version: 2.1
Name: diva-framework
Version: 0.0.6
Summary: The DIVA Framework is a software framework designedto provide an architecture and a set of software modules whichwill facilitate the development of DIVA analytics
Home-page: https://github.com/Kitware/DIVA
Author: Kitware, Inc.
Author-email: diva-framework@kitware.com
License: BSD 3-Clause
Platform: linux
Platform: Unix
Classifier: Development Status :: 3 - Alpha
Classifier: Programming Language :: Python :: 3.5
Classifier: Programming Language :: Python :: 3.6
Classifier: Programming Language :: Python :: 3.7
Classifier: Programming Language :: Python :: 3.8
Classifier: Operating System :: Unix
Classifier: Intended Audience :: Developers
Classifier: Intended Audience :: Science/Research
Classifier: Topic :: Scientific/Engineering :: Artificial Intelligence
Requires-Python: >=3.5
Requires-Dist: kwiver (==1.4.5)
Requires-Dist: opencv-python
